odoo/addons/purchase_commercial_partner/README.rst
odoo/addons/purchase_commercial_partner/__init__.py
odoo/addons/purchase_commercial_partner/__manifest__.py
odoo/addons/purchase_commercial_partner/i18n/de.po
odoo/addons/purchase_commercial_partner/i18n/es.po
odoo/addons/purchase_commercial_partner/i18n/es_ES.po
odoo/addons/purchase_commercial_partner/i18n/es_PE.po
odoo/addons/purchase_commercial_partner/i18n/fr.po
odoo/addons/purchase_commercial_partner/i18n/fr_BE.po
odoo/addons/purchase_commercial_partner/i18n/gl.po
odoo/addons/purchase_commercial_partner/i18n/hr.po
odoo/addons/purchase_commercial_partner/i18n/it.po
odoo/addons/purchase_commercial_partner/i18n/nl.po
odoo/addons/purchase_commercial_partner/i18n/nl_NL.po
odoo/addons/purchase_commercial_partner/i18n/pt_BR.po
odoo/addons/purchase_commercial_partner/i18n/purchase_commercial_partner.pot
odoo/addons/purchase_commercial_partner/i18n/ro.po
odoo/addons/purchase_commercial_partner/i18n/sl.po
odoo/addons/purchase_commercial_partner/i18n/sv.po
odoo/addons/purchase_commercial_partner/i18n/vi_VN.po
odoo/addons/purchase_commercial_partner/models/__init__.py
odoo/addons/purchase_commercial_partner/models/purchase_order.py
odoo/addons/purchase_commercial_partner/readme/CONTRIBUTORS.md
odoo/addons/purchase_commercial_partner/readme/DESCRIPTION.md
odoo/addons/purchase_commercial_partner/readme/USAGE.md
odoo/addons/purchase_commercial_partner/static/description/icon.png
odoo/addons/purchase_commercial_partner/static/description/index.html
odoo/addons/purchase_commercial_partner/tests/__init__.py
odoo/addons/purchase_commercial_partner/tests/test_purchase_commercial_partner.py
odoo/addons/purchase_commercial_partner/views/purchase_order.xml
odoo/addons/purchase_commercial_partner/views/purchase_report.xml
odoo_addon_purchase_commercial_partner-18.0.1.0.0.3.dist-info/METADATA
odoo_addon_purchase_commercial_partner-18.0.1.0.0.3.dist-info/WHEEL
odoo_addon_purchase_commercial_partner-18.0.1.0.0.3.dist-info/top_level.txt
odoo_addon_purchase_commercial_partner-18.0.1.0.0.3.dist-info/RECORD
